LICENSE.txt
MANIFEST.in
README.rst
pyproject.toml
thug/__init__.py
thug/thug.py
thug.egg-info/PKG-INFO
thug.egg-info/SOURCES.txt
thug.egg-info/dependency_links.txt
thug.egg-info/entry_points.txt
thug.egg-info/requires.txt
thug.egg-info/top_level.txt
thug.egg-info/zip-safe
thug/ActiveX/ActiveX.py
thug/ActiveX/CLSID.py
thug/ActiveX/__init__.py
thug/ActiveX/modules/AOLAttack.py
thug/ActiveX/modules/AcroPDF.py
thug/ActiveX/modules/AdodbRecordset.py
thug/ActiveX/modules/AdodbStream.py
thug/ActiveX/modules/AnswerWorks.py
thug/ActiveX/modules/AolAmpX.py
thug/ActiveX/modules/AolICQ.py
thug/ActiveX/modules/BaiduBar.py
thug/ActiveX/modules/BitDefender.py
thug/ActiveX/modules/CABrightStor.py
thug/ActiveX/modules/CGAgent.py
thug/ActiveX/modules/Comodo.py
thug/ActiveX/modules/ConnectAndEnterRoom.py
thug/ActiveX/modules/CreativeSoftAttack.py
thug/ActiveX/modules/DLinkMPEG.py
thug/ActiveX/modules/DPClient.py
thug/ActiveX/modules/DVRHOSTWeb.py
thug/ActiveX/modules/DirectShow.py
thug/ActiveX/modules/DivX.py
thug/ActiveX/modules/Domino.py
thug/ActiveX/modules/EnjoySAP.py
thug/ActiveX/modules/FacebookPhotoUploader.py
thug/ActiveX/modules/File.py
thug/ActiveX/modules/FileUploader.py
thug/ActiveX/modules/Folder.py
thug/ActiveX/modules/GLIEDown2.py
thug/ActiveX/modules/GatewayWeblaunch.py
thug/ActiveX/modules/Gogago.py
thug/ActiveX/modules/GomWeb.py
thug/ActiveX/modules/HPInfo.py
thug/ActiveX/modules/ICQToolbar.py
thug/ActiveX/modules/IMWebControl.py
thug/ActiveX/modules/InternetCleverSuite.py
thug/ActiveX/modules/JavaDeploymentToolkit.py
thug/ActiveX/modules/JetAudioDownloadFromMusicStore.py
thug/ActiveX/modules/Kingsoft.py
thug/ActiveX/modules/MSRICHTXT.py
thug/ActiveX/modules/MSVFP.py
thug/ActiveX/modules/MSXML2DOMDocument.py
thug/ActiveX/modules/MacrovisionFlexNet.py
thug/ActiveX/modules/MicrosoftWorks7Attack.py
thug/ActiveX/modules/MicrosoftXMLDOM.py
thug/ActiveX/modules/MicrosoftXMLHTTP.py
thug/ActiveX/modules/Move.py
thug/ActiveX/modules/MyspaceUploader.py
thug/ActiveX/modules/NCTAudioFile2.py
thug/ActiveX/modules/NamoInstaller.py
thug/ActiveX/modules/NeoTracePro.py
thug/ActiveX/modules/NessusScanCtrl.py
thug/ActiveX/modules/OfficeOCX.py
