Metadata-Version: 2.4
Name: thug
Version: 6.18
Summary: Low-interaction honeyclient Thug
Author-email: Angelo Dell'Aera <angelo.dellaera@honeynet.org>
Maintainer-email: Angelo Dell'Aera <angelo.dellaera@honeynet.org>
License: GPLv2
Project-URL: homepage, https://github.com/buffer/thug
Project-URL: documentation, https://thug-honeyclient.readthedocs.io/en/latest/
Project-URL: bugs, https://github.com/buffer/thug/issues
Project-URL: funding, https://buffer.github.io/thug/
Keywords: honeyclient,low-interaction,client-honeypot,security-tools
Platform: linux
Platform: darwin
Classifier: Development Status :: 5 - Production/Stable
Classifier: Environment :: Console
Classifier: Intended Audience :: Developers
Classifier: License :: OSI Approved :: GNU General Public License v2 (GPLv2)
Classifier: Operating System :: POSIX :: Linux
Classifier: Operating System :: MacOS :: MacOS X
Classifier: Programming Language :: Python :: 3
Classifier: Programming Language :: Python :: 3.9
Classifier: Programming Language :: Python :: 3.10
Classifier: Programming Language :: Python :: 3.11
Classifier: Programming Language :: Python :: 3.12
Classifier: Programming Language :: Python :: 3.13
Classifier: Programming Language :: Python :: 3.14
Classifier: Topic :: Security
Requires-Python: >=3.9
License-File: LICENSE.txt
Requires-Dist: appdirs==1.4.4
Requires-Dist: beautifulsoup4==4.14.2
Requires-Dist: charset-normalizer==3.4.4
Requires-Dist: cssutils==2.11.1
Requires-Dist: dhash==1.4
Requires-Dist: html5lib==1.1
Requires-Dist: importlib-resources==6.0.1; python_version < "3.9"
Requires-Dist: lxml==6.0.2
Requires-Dist: networkx==3.2.1; python_version < "3.10"
Requires-Dist: networkx==3.4.2; python_version == "3.10"
Requires-Dist: networkx==3.5; python_version > "3.10"
Requires-Dist: pefile==2024.8.26
Requires-Dist: pillow==11.3.0; python_version < "3.10"
Requires-Dist: pillow==12.0.0; python_version > "3.9"
Requires-Dist: promise==2.3
Requires-Dist: pylibemu==1.0
Requires-Dist: pymongo==4.15.3
Requires-Dist: pysocks==1.7.1
Requires-Dist: python-magic==0.4.27
Requires-Dist: rarfile==4.2
Requires-Dist: requests==2.32.5
Requires-Dist: requests-futures==1.0.2
Requires-Dist: setuptools>=65.5.1
Requires-Dist: ssdeep==3.4
Requires-Dist: stpyv8==13.1.201.22
Requires-Dist: yara-python==4.5.4
Requires-Dist: zope.interface==8.0.1
Provides-Extra: elasticsearch
Requires-Dist: elasticsearch; extra == "elasticsearch"
Provides-Extra: exploitgraph
Requires-Dist: pygraphviz; extra == "exploitgraph"
Provides-Extra: image
Requires-Dist: pytesseract; extra == "image"
Requires-Dist: weasyprint; extra == "image"
Provides-Extra: shellcode
Requires-Dist: speakeasy-emulator; extra == "shellcode"
Provides-Extra: documentation
Requires-Dist: sphinx; extra == "documentation"
Requires-Dist: python-docs-theme; extra == "documentation"
Provides-Extra: test
Requires-Dist: thug[elasticsearch,exploitgraph,image,shellcode]; extra == "test"
Requires-Dist: mock; extra == "test"
Requires-Dist: pydantic>=2.9.2; extra == "test"
Requires-Dist: pre-commit; extra == "test"
Requires-Dist: pytest; extra == "test"
Requires-Dist: pytest-cov; extra == "test"
Requires-Dist: pytest-timeout; extra == "test"
Requires-Dist: safety; extra == "test"
Requires-Dist: tox; extra == "test"
Dynamic: license-file
